dictionary/__init__.py
dictionary/dictionary.py
osama_tanveer_very_simple_dictionary-2.0.1.dist-info/METADATA
osama_tanveer_very_simple_dictionary-2.0.1.dist-info/WHEEL
osama_tanveer_very_simple_dictionary-2.0.1.dist-info/top_level.txt
osama_tanveer_very_simple_dictionary-2.0.1.dist-info/RECORD
