Metadata-Version: 2.1
Name: osama-tanveer-very-simple-dictionary
Version: 2.0.1
Summary: UNKNOWN
Author: Osama Tanveer
License: UNKNOWN
Platform: UNKNOWN
Requires-Python: >=3.8
Requires-Dist: requests (>=2.23.0)
